LICENSE
MANIFEST.in
README.md
setup.cfg
setup.py
aab/__init__.py
aab/builder.py
aab/cli.py
aab/config.py
aab/git.py
aab/schema.json
aab/ui.py
aab/utils.py
aab.egg-info/PKG-INFO
aab.egg-info/SOURCES.txt
aab.egg-info/dependency_links.txt
aab.egg-info/entry_points.txt
aab.egg-info/requires.txt
aab.egg-info/top_level.txt