Metadata-Version: 2.1
Name: aab
Version: 0.1.4
Summary: Anki Add-on Builder
Home-page: https://github.com/glutanimate/anki-addon-builder
Author: Aristotelis P. (Glutanimate)
License: UNKNOWN
Project-URL: Bug Reports, https://github.com/glutanimate/anki-addon-builder/issues
Project-URL: Funding, https://glutanimate.com/support-my-work/
Project-URL: Source, https://github.com/glutanimate/anki-addon-builder
Keywords: anki development build-tools
Platform: UNKNOWN
Classifier: Development Status :: 3 - Alpha
Classifier: Intended Audience :: Developers
Classifier: Topic :: Software Development :: Build Tools
Classifier: License :: OSI Approved :: GNU Affero General Public License v3
Classifier: Programming Language :: Python :: 2
Classifier: Programming Language :: Python :: 2.7
Classifier: Programming Language :: Python :: 3
Classifier: Programming Language :: Python :: 3.5
Classifier: Programming Language :: Python :: 3.6
Classifier: Programming Language :: Python :: 3.7
Classifier: Operating System :: POSIX
Classifier: Operating System :: MacOS
Requires-Python: >=2.7, !=3.0.*, !=3.1.*, !=3.2.*, !=3.3.*, !=3.4.*, <4
Provides-Extra: anki21
